AUI/generator.sv
module aui_generator 
#(
    parameter DATA_WIDTH = 64, 
    parameter NUMBER_LANES = 16
)
(
    input logic clk,
    input logic rst_n,
    input logic [DATA_WIDTH-1:0]i_data,
    output logic [DATA_WIDTH-1:0] tx_lane[NUMBER_LANES-1:0]  // 16 lanes, each 64-bit wide
);


    always_ff @(posedge clk or negedge rst_n) begin
        if (!rst_n) begin
            for (int i = 0; i < NUMBER_LANES; i++) begin
                tx_lane[i] <= {DATA_WIDTH{1'b0}};
            end
        end else begin
            for (int i = 0; i < NUMBER_LANES; i++) begin                
                tx_lane[i] <= i_data; // Broadcast i_data to all lanes
            end
        end
    end

endmodule

AUI/testbench.sv
module aui_testbench;
    // Parameters
    parameter DATA_WIDTH = 64;
    parameter NUMBER_LANES = 16;

    // Signals
    logic clk;
    logic rst_n;
    wire [DATA_WIDTH-1:0]  tx_lane[NUMBER_LANES-1:0];
    logic [DATA_WIDTH-1:0]i_data;

    // Instantiate the AUI generator
    aui_generator #(
        .DATA_WIDTH(DATA_WIDTH),
        .NUMBER_LANES(NUMBER_LANES)
    ) generator_aui (
        .clk(clk),
        .rst_n(rst_n),
        .i_data(i_data),
        .tx_lane(tx_lane)
    );

    // Clock generation
    initial begin
        clk = 0;
        forever #5 clk = ~clk; // 100 MHz clock
    end

    // Reset generation
    initial begin
        rst_n = 0;
        i_data = 64'hFFFF;
        #20 rst_n = 1;
        #500;
        i_data = 64'h5555554;
    end

    // Simulation control
    initial begin
        // Run the simulation for a specific time
        #1000;
        $finish;
    end

    // Dump waveforms for GTKWave
    initial begin
    $dumpfile("aui_testbench.vcd");   // Specify VCD file for gtkwave
    $dumpvars(0, aui_testbench); // Start dumping signals from the top module
end

    // Monitor and display lane values (optional for debugging)
    /*always @(posedge clk) begin
        if (rst_n) begin
            for (int i = 0; i < NUMBER_LANES; i++) begin
                $display("Time: %0t, tx_lane[%0d] = %h", $time, i, tx_lane[i]);
            end
        end
    end*/
endmodule

AUI/aui_testbench.vcd
$date
	Mon Oct 21 16:54:55 2024
$end
$version
	Icarus Verilog
$end
$timescale
	1s
$end
$scope module aui_testbench $end
$var reg 1 ! clk $end
$var reg 64 " i_data [63:0] $end
$var reg 1 # rst_n $end
$scope module generator_aui $end
$var wire 1 ! clk $end
$var wire 64 $ i_data [63:0] $end
$var wire 1 # rst_n $end
$scope begin $ivl_for_loop0 $end
$var integer 32 % i [31:0] $end
$upscope $end
$scope begin $ivl_for_loop1 $end
$var integer 32 & i [31:0] $end
$upscope $end
$upscope $end
$upscope $end
$enddefinitions $end
#0
$dumpvars
b0 &
b10000 %
b1111111111111111 $
0#
b1111111111111111 "
0!
$end
#5
b10000 %
1!
#10
0!
#15
b10000 %
1!
#20
0!
1#
#25
b10000 &
1!
#30
0!
#35
b10000 &
1!
#40
0!
#45
b10000 &
1!
#50
0!
#55
b10000 &
1!
#60
0!
#65
b10000 &
1!
#70
0!
#75
b10000 &
1!
#80
0!
#85
b10000 &
1!
#90
0!
#95
b10000 &
1!
#100
0!
#105
b10000 &
1!
#110
0!
#115
b10000 &
1!
#120
0!
#125
b10000 &
1!
#130
0!
#135
b10000 &
1!
#140
0!
#145
b10000 &
1!
#150
0!
#155
b10000 &
1!
#160
0!
#165
b10000 &
1!
#170
0!
#175
b10000 &
1!
#180
0!
#185
b10000 &
1!
#190
0!
#195
b10000 &
1!
#200
0!
#205
b10000 &
1!
#210
0!
#215
b10000 &
1!
#220
0!
#225
b10000 &
1!
#230
0!
#235
b10000 &
1!
#240
0!
#245
b10000 &
1!
#250
0!
#255
b10000 &
1!
#260
0!
#265
b10000 &
1!
#270
0!
#275
b10000 &
1!
#280
0!
#285
b10000 &
1!
#290
0!
#295
b10000 &
1!
#300
0!
#305
b10000 &
1!
#310
0!
#315
b10000 &
1!
#320
0!
#325
b10000 &
1!
#330
0!
#335
b10000 &
1!
#340
0!
#345
b10000 &
1!
#350
0!
#355
b10000 &
1!
#360
0!
#365
b10000 &
1!
#370
0!
#375
b10000 &
1!
#380
0!
#385
b10000 &
1!
#390
0!
#395
b10000 &
1!
#400
0!
#405
b10000 &
1!
#410
0!
#415
b10000 &
1!
#420
0!
#425
b10000 &
1!
#430
0!
#435
b10000 &
1!
#440
0!
#445
b10000 &
1!
#450
0!
#455
b10000 &
1!
#460
0!
#465
b10000 &
1!
#470
0!
#475
b10000 &
1!
#480
0!
#485
b10000 &
1!
#490
0!
#495
b10000 &
1!
#500
0!
#505
b10000 &
1!
#510
0!
#515
b10000 &
1!
#520
0!
b101010101010101010101010100 "
b101010101010101010101010100 $
#525
b10000 &
1!
#530
0!
#535
b10000 &
1!
#540
0!
#545
b10000 &
1!
#550
0!
#555
b10000 &
1!
#560
0!
#565
b10000 &
1!
#570
0!
#575
b10000 &
1!
#580
0!
#585
b10000 &
1!
#590
0!
#595
b10000 &
1!
#600
0!
#605
b10000 &
1!
#610
0!
#615
b10000 &
1!
#620
0!
#625
b10000 &
1!
#630
0!
#635
b10000 &
1!
#640
0!
#645
b10000 &
1!
#650
0!
#655
b10000 &
1!
#660
0!
#665
b10000 &
1!
#670
0!
#675
b10000 &
1!
#680
0!
#685
b10000 &
1!
#690
0!
#695
b10000 &
1!
#700
0!
#705
b10000 &
1!
#710
0!
#715
b10000 &
1!
#720
0!
#725
b10000 &
1!
#730
0!
#735
b10000 &
1!
#740
0!
#745
b10000 &
1!
#750
0!
#755
b10000 &
1!
#760
0!
#765
b10000 &
1!
#770
0!
#775
b10000 &
1!
#780
0!
#785
b10000 &
1!
#790
0!
#795
b10000 &
1!
#800
0!
#805
b10000 &
1!
#810
0!
#815
b10000 &
1!
#820
0!
#825
b10000 &
1!
#830
0!
#835
b10000 &
1!
#840
0!
#845
b10000 &
1!
#850
0!
#855
b10000 &
1!
#860
0!
#865
b10000 &
1!
#870
0!
#875
b10000 &
1!
#880
0!
#885
b10000 &
1!
#890
0!
#895
b10000 &
1!
#900
0!
#905
b10000 &
1!
#910
0!
#915
b10000 &
1!
#920
0!
#925
b10000 &
1!
#930
0!
#935
b10000 &
1!
#940
0!
#945
b10000 &
1!
#950
0!
#955
b10000 &
1!
#960
0!
#965
b10000 &
1!
#970
0!
#975
b10000 &
1!
#980
0!
#985
b10000 &
1!
#990
0!
#995
b10000 &
1!
